Workbook

Sheet Referencia_24
A1: Caso | B1: Área | C1: Tema | D1: Tipo de prueba | E1: Entrada A | F1: Entrada B | G1: Respuesta A | H1: Respuesta B | I1: IEE Semántica | J1: IEE Objetivo | K1: IEE Cognitivo | L1: IEE Alcance | M1: IEE Neutralidad | N1: IEE Ref | O1: IPE A Definición | P1: IPE A Causalidad | Q1: IPE A Ejemplificación | R1: IPE A Aplicación | S1: IPE A Ref | T1: IPE B Definición | U1: IPE B Causalidad | V1: IPE B Ejemplificación | W1: IPE B Aplicación | X1: IPE B Ref | Y1: ΔIPE Ref | Z1: |ΔIPE| Ref | AA1: Comportamiento esperado
A2: PILOT-001 | B2: Redes | C2: Latencia | D2: Equivalencia fuerte / diferencia clara de profundidad | E2: Explique qué es la latencia en redes de computadoras y cómo puede afectar una comunicación en tiempo real. | F2: Describa qué se entiende por latencia en una red informática y de qué manera influye en aplicaciones de tiempo real. | G2: La latencia es el tiempo que tarda la información en desplazarse desde un origen hasta un destino. Puede aumentar por la distancia, el procesamiento de los dispositivos intermedios y la congestión. En una videollamada, una latencia elevada provoca retrasos entre lo que una persona dice y lo que la otra escucha; por ello, reducirla mejora la interacción en aplicaciones en tiempo real. | H2: La latencia es el retraso que existe cuando los datos viajan por una red. Puede afectar algunas aplicaciones porque la información tarda más en llegar. | I2: 4 | J2: 4 | K2: 4 | L2: 4 | M2: 4 | N2: =SUM(I2:M2)/20*100 -> 100 | O2: 3 | P2: 3 | Q2: 3 | R2: 3 | S2: =SUM(O2:R2)/16*100 -> 75 | T2: 2 | U2: 1 | V2: 0 | W2: 1 | X2: =SUM(T2:W2)/16*100 -> 25 | Y2: =S2-X2 -> 50 | Z2: =ABS(Y2) -> 50 | AA2: IEE alto; IPE-A claramente superior.
A3: PILOT-002 | B3: Bases de datos | C3: Índices | D3: Equivalencia fuerte / control de verborrea | E3: Explique cómo un índice puede mejorar el rendimiento de las consultas en una base de datos. | F3: Describa de qué manera los índices contribuyen al rendimiento de las consultas en una base de datos. | G3: Un índice mantiene una estructura auxiliar que permite localizar registros sin recorrer toda la tabla. Por ejemplo, un índice basado en un árbol B reduce las páginas que deben examinarse para encontrar un valor. Esto acelera muchas búsquedas, aunque mantener el índice añade costo durante inserciones, eliminaciones y actualizaciones. | H3: Los índices son elementos muy importantes dentro de las bases de datos modernas y se utilizan en muchos sistemas. Ayudan a que la información pueda ser manejada de forma eficiente y organizada. Son útiles en aplicaciones empresariales, sistemas grandes y diferentes escenarios donde el rendimiento es importante. Por ello, los índices son considerados una herramienta valiosa para las bases de datos. | I3: 4 | J3: 4 | K3: 4 | L3: 4 | M3: 4 | N3: =SUM(I3:M3)/20*100 -> 100 | O3: 3 | P3: 4 | Q3: 3 | R3: 3 | S3: =SUM(O3:R3)/16*100 -> 81.25 | T3: 2 | U3: 1 | V3: 1 | W3: 1 | X3: =SUM(T3:W3)/16*100 -> 31.25 | Y3: =S3-X3 -> 50 | Z3: =ABS(Y3) -> 50 | AA3: A debe superar a B pese a que B es más larga.
A4: PILOT-003 | B4: Redes | C4: TCP | D4: Equivalencia fuerte / respuestas de profundidad similar | E4: Explique cómo TCP proporciona una transmisión confiable de datos. | F4: Describa los mecanismos mediante los cuales TCP garantiza la entrega confiable de información. | G4: TCP utiliza números de secuencia, confirmaciones y retransmisiones. Los números de secuencia permiten ordenar los segmentos, mientras que las confirmaciones indican al emisor qué información llegó correctamente. Si un segmento no es confirmado dentro del tiempo esperado, puede retransmitirse. Así se compensan pérdidas y desorden durante la comunicación. | H4: TCP numera los segmentos para conservar el orden y utiliza acknowledgments para confirmar la recepción. Cuando determinados datos no son confirmados, el emisor puede retransmitirlos. Estos mecanismos permiten recuperar información perdida y entregar al receptor el flujo de datos en el orden esperado. | I4: 4 | J4: 4 | K4: 4 | L4: 4 | M4: 4 | N4: =SUM(I4:M4)/20*100 -> 100 | O4: 3 | P4: 4 | Q4: 1 | R4: 2 | S4: =SUM(O4:R4)/16*100 -> 62.5 | T4: 3 | U4: 4 | V4: 1 | W4: 2 | X4: =SUM(T4:W4)/16*100 -> 62.5 | Y4: =S4-X4 -> 0 | Z4: =ABS(Y4) -> 0 | AA4: IPE muy cercanos; ΔIPE pequeño.
A5: PILOT-004 | B5: Sistemas operativos | C5: Memoria virtual | D5: Equivalencia fuerte / diferencia clara | E5: Explique qué es la memoria virtual y cómo contribuye al funcionamiento de un sistema operativo. | F5: Describa qué se entiende por memoria virtual y cuál es su utilidad dentro de un sistema operativo. | G5: La memoria virtual permite que cada proceso disponga de un espacio de direcciones lógico que puede exceder la RAM disponible. El sistema operativo mantiene en memoria principal las páginas necesarias y almacena temporalmente otras en almacenamiento secundario. Cuando una página requerida no está en RAM ocurre un fallo de página y debe recuperarse. Esto facilita aislamiento y ejecución de programas grandes, aunque un exceso de intercambios degrada el rendimiento. | H5: La memoria virtual es una función del sistema operativo que permite disponer de más memoria para ejecutar programas cuando la RAM no es suficiente. | I5: 4 | J5: 4 | K5: 4 | L5: 4 | M5: 4 | N5: =SUM(I5:M5)/20*100 -> 100 | O5: 4 | P5: 4 | Q5: 2 | R5: 3 | S5: =SUM(O5:R5)/16*100 -> 81.25 | T5: 2 | U5: 1 | V5: 0 | W5: 1 | X5: =SUM(T5:W5)/16*100 -> 25 | Y5: =S5-X5 -> 56.25 | Z5: =ABS(Y5) -> 56.25 | AA5: IPE-A claramente superior.
A6: PILOT-005 | B6: Programación | C6: Recursividad | D6: Equivalencia fuerte / ejemplo vs ejemplo | E6: Explique mediante un ejemplo cómo funciona la recursividad en programación. | F6: Describa el funcionamiento de la recursividad utilizando un caso ilustrativo. | G6: La recursividad ocurre cuando una función se llama a sí misma para resolver una versión más pequeña del problema y se detiene al alcanzar un caso base. Por ejemplo, factorial(n) puede calcular n por factorial(n-1), mientras que factorial(0) devuelve 1. Cada llamada reduce el problema hasta llegar al caso base y luego se resuelven las llamadas pendientes. | H6: Una función recursiva se invoca a sí misma. Por ejemplo, para calcular un factorial se puede llamar nuevamente a la función usando un número menor hasta llegar a cero. En ese punto se detienen las llamadas y se obtiene el resultado. | I6: 4 | J6: 4 | K6: 4 | L6: 4 | M6: 4 | N6: =SUM(I6:M6)/20*100 -> 100 | O6: 4 | P6: 3 | Q6: 4 | R6: 3 | S6: =SUM(O6:R6)/16*100 -> 87.5 | T6: 3 | U6: 2 | V6: 3 | W6: 2 | X6: =SUM(T6:W6)/16*100 -> 62.5 | Y6: =S6-X6 -> 25 | Z6: =ABS(Y6) -> 25 | AA6: Ambos razonables; A moderadamente superior.
A7: PILOT-006 | B7: Algoritmos | C7: Búsqueda binaria | D7: Caso fronterizo de equivalencia | E7: Explique cómo la búsqueda binaria reduce progresivamente el espacio de búsqueda. | F7: Describa por qué la búsqueda binaria puede localizar elementos eficientemente en una colección ordenada. | G7: La búsqueda binaria compara el objetivo con el elemento central de una colección ordenada. Si no coincide, descarta la mitad que no puede contenerlo y repite el proceso sobre la mitad restante. Como el espacio de búsqueda se divide aproximadamente entre dos en cada paso, el número de comparaciones crece de forma logarítmica. | H7: La búsqueda binaria es eficiente porque aprovecha que los datos están ordenados. Revisa el valor central y elimina una parte de los elementos que ya no necesita revisar. Después continúa hasta encontrar el valor o determinar que no existe. | I7: 4 | J7: 3 | K7: 4 | L7: 3 | M7: 3 | N7: =SUM(I7:M7)/20*100 -> 85 | O7: 4 | P7: 4 | Q7: 1 | R7: 2 | S7: =SUM(O7:R7)/16*100 -> 68.75 | T7: 3 | U7: 3 | V7: 1 | W7: 2 | X7: =SUM(T7:W7)/16*100 -> 56.25 | Y7: =S7-X7 -> 12.5 | Z7: =ABS(Y7) -> 12.5 | AA7: IEE medio-alto; IPE relativamente cercanos.
A8: PILOT-007 | B8: Redes | C8: Modelo OSI | D8: Equivalencia parcial intencional | E8: Explique qué es el modelo OSI y cuál es su propósito en las comunicaciones de red. | F8: Enumere las siete capas del modelo OSI en orden. | G8: El modelo OSI es un marco conceptual que divide la comunicación de red en siete capas para separar responsabilidades y facilitar el diseño, interoperabilidad y diagnóstico. Sus capas son física, enlace de datos, red, transporte, sesión, presentación y aplicación. Cada una agrupa funciones específicas dentro del proceso de comunicación. | H8: Las capas son: física, enlace de datos, red, transporte, sesión, presentación y aplicación. | I8: 2 | J8: 0 | K8: 1 | L8: 1 | M8: 0 | N8: =SUM(I8:M8)/20*100 -> 20 | O8: 4 | P8: 3 | Q8: 2 | R8: 3 | S8: =SUM(O8:R8)/16*100 -> 75 | T8: 2 | U8: 0 | V8: 0 | W8: 0 | X8: =SUM(T8:W8)/16*100 -> 12.5 | Y8: =S8-X8 -> 62.5 | Z8: =ABS(Y8) -> 62.5 | AA8: IEE bajo/revisión fuerte.
A9: PILOT-008 | B9: Concurrencia | C9: Condición de carrera | D9: Equivalencia parcial intencional | E9: Explique por qué se producen condiciones de carrera en sistemas concurrentes. | F9: Describa qué es una condición de carrera en programación concurrente. | G9: Una condición de carrera aparece cuando varios hilos o procesos acceden a un recurso compartido y el resultado depende del orden temporal de operaciones no coordinadas. Si dos hilos leen y modifican el mismo valor sin sincronización, una actualización puede sobrescribir a la otra. Mecanismos como mutex o semáforos controlan el acceso para evitar esa dependencia del intercalado. | H9: Una condición de carrera es un problema que ocurre cuando varios hilos trabajan con los mismos datos y el resultado puede cambiar dependiendo del orden en que se ejecutan. | I9: 4 | J9: 2 | K9: 2 | L9: 3 | M9: 2 | N9: =SUM(I9:M9)/20*100 -> 65 | O9: 4 | P9: 4 | Q9: 3 | R9: 3 | S9: =SUM(O9:R9)/16*100 -> 87.5 | T9: 3 | U9: 2 | V9: 1 | W9: 1 | X9: =SUM(T9:W9)/16*100 -> 43.75 | Y9: =S9-X9 -> 43.75 | Z9: =ABS(Y9) -> 43.75 | AA9: IEE intermedio; A superior en causalidad.
A10: PILOT-009 | B10: Estructuras de datos | C10: Pila y cola | D10: No equivalentes / trampa temática | E10: Explique el funcionamiento de una pila como estructura de datos. | F10: Explique el funcionamiento de una cola como estructura de datos. | G10: Una pila sigue el principio LIFO: el último elemento insertado es el primero en retirarse. Las operaciones principales son push para insertar en la parte superior y pop para retirar desde ella. Un ejemplo es la pila de llamadas de un programa, donde la llamada más reciente debe finalizar antes de regresar a la anterior. | H10: Una cola sigue el principio FIFO: el primer elemento insertado es el primero en salir. Normalmente se agrega por un extremo y se retira por el otro. Por ejemplo, una cola de impresión procesa los trabajos aproximadamente en el orden en que fueron recibidos. | I10: 1 | J10: 1 | K10: 4 | L10: 1 | M10: 0 | N10: =SUM(I10:M10)/20*100 -> 35 | O10: 4 | P10: 3 | Q10: 4 | R10: 3 | S10: =SUM(O10:R10)/16*100 -> 87.5 | T10: 4 | U10: 3 | V10: 4 | W10: 3 | X10: =SUM(T10:W10)/16*100 -> 87.5 | Y10: =S10-X10 -> 0 | Z10: =ABS(Y10) -> 0 | AA10: IEE bajo aunque las respuestas tengan profundidad similar.
A11: PILOT-010 | B11: Bases de datos | C11: Claves | D11: No equivalentes / ampliación del objetivo | E11: Explique qué es una clave primaria en una base de datos relacional. | F11: Compare una clave primaria con una clave foránea en una base de datos relacional. | G11: Una clave primaria es un atributo o conjunto de atributos que identifica de manera única cada fila de una tabla. Sus valores no deben duplicarse y normalmente no pueden ser nulos. Por ejemplo, un identificador de estudiante puede actuar como clave primaria si distingue a cada registro. | H11: Una clave primaria identifica de forma única las filas de su propia tabla. Una clave foránea, en cambio, contiene valores que hacen referencia a una clave candidata, normalmente primaria, de otra tabla o de la misma tabla. La primera contribuye a la identidad de los registros y la segunda permite representar relaciones entre ellos. | I11: 3 | J11: 1 | K11: 2 | L11: 2 | M11: 1 | N11: =SUM(I11:M11)/20*100 -> 45 | O11: 4 | P11: 2 | Q11: 4 | R11: 3 | S11: =SUM(O11:R11)/16*100 -> 81.25 | T11: 4 | U11: 4 | V11: 2 | W11: 3 | X11: =SUM(T11:W11)/16*100 -> 81.25 | Y11: =S11-X11 -> 0 | Z11: =ABS(Y11) -> 0 | AA11: IEE bajo/intermedio por ampliación del objetivo.
A12: PILOT-011 | B12: Seguridad | C12: Hashing | D12: Equivalencia fuerte / respuesta A más profunda | E12: Explique qué es una función hash criptográfica y qué propiedades la hacen útil en seguridad. | F12: Describa el concepto de hash criptográfico y las propiedades que permiten utilizarlo en aplicaciones de seguridad. | G12: Una función hash criptográfica transforma datos de longitud arbitraria en un resumen de longitud fija. Para usos de seguridad se espera resistencia a preimagen, segunda preimagen y colisiones, además de un comportamiento donde pequeños cambios en la entrada alteren ampliamente el resultado. Estas propiedades permiten verificar integridad y participar en construcciones como firmas digitales, aunque un hash por sí solo no cifra la información. | H12: Un hash criptográfico convierte información en un valor de tamaño fijo. Debe ser difícil obtener el contenido original y también debe ser difícil encontrar dos entradas con el mismo resultado. Se usa para comprobar datos y en diferentes mecanismos de seguridad. | I12: 4 | J12: 4 | K12: 4 | L12: 4 | M12: 4 | N12: =SUM(I12:M12)/20*100 -> 100 | O12: 4 | P12: 4 | Q12: 3 | R12: 4 | S12: =SUM(O12:R12)/16*100 -> 93.75 | T12: 3 | U12: 3 | V12: 1 | W12: 2 | X12: =SUM(T12:W12)/16*100 -> 56.25 | Y12: =S12-X12 -> 37.5 | Z12: =ABS(Y12) -> 37.5 | AA12: IEE alto; A superior por precisión y desarrollo.
A13: PILOT-012 | B13: Ingeniería de software | C13: Pruebas unitarias | D13: Equivalencia fuerte / B con ejemplos | E13: Explique cuál es el propósito de las pruebas unitarias durante el desarrollo de software. | F13: Describa para qué se utilizan las pruebas unitarias dentro de un proyecto de software. | G13: Las pruebas unitarias verifican de forma aislada unidades pequeñas de comportamiento, como funciones o métodos. Permiten detectar regresiones rápidamente porque una modificación que rompe un comportamiento previamente comprobado provoca un fallo reproducible. También favorecen refactorizaciones más seguras al ofrecer retroalimentación automática sobre contratos existentes. | H13: Las pruebas unitarias sirven para comprobar partes pequeñas del programa. Por ejemplo, se puede probar una función que suma números, una función que valida un correo o un método que calcula un descuento. Son muy utilizadas durante el desarrollo de software. | I13: 4 | J13: 4 | K13: 4 | L13: 4 | M13: 4 | N13: =SUM(I13:M13)/20*100 -> 100 | O13: 4 | P13: 4 | Q13: 1 | R13: 4 | S13: =SUM(O13:R13)/16*100 -> 81.25 | T13: 3 | U13: 1 | V13: 4 | W13: 2 | X13: =SUM(T13:W13)/16*100 -> 62.5 | Y13: =S13-X13 -> 18.75 | Z13: =ABS(Y13) -> 18.75 | AA13: A superior en causalidad; B superior en ejemplificación.
... A25: PILOT-024 | B25: Sistemas distribuidos | C25: Consistencia | D25: Equivalencia fuerte / dos respuestas igualmente profundas | E25: Explique qué significa consistencia eventual en un sistema distribuido. | F25: Describa el concepto de consistencia eventual aplicado a sistemas distribuidos. | G25: La consistencia eventual permite que distintas réplicas presenten temporalmente valores diferentes después de una actualización, pero establece que, si dejan de ocurrir nuevas modificaciones y la comunicación continúa, las réplicas convergerán hacia un estado común. Este modelo favorece disponibilidad y operación distribuida en ciertos escenarios, a cambio de aceptar lecturas temporalmente desactualizadas. | H25: En un sistema con consistencia eventual, una escritura no tiene que hacerse visible inmediatamente en todas las réplicas. Durante un intervalo pueden observarse estados diferentes; sin embargo, en ausencia de nuevas actualizaciones, la propagación termina haciendo que las copias converjan. Por ello se acepta inconsistencia temporal a cambio de otras propiedades operativas. | I25: 4 | J25: 4 | K25: 4 | L25: 4 | M25: 4 | N25: =SUM(I25:M25)/20*100 -> 100 | O25: 4 | P25: 4 | Q25: 1 | R25: 4 | S25: =SUM(O25:R25)/16*100 -> 81.25 | T25: 4 | U25: 4 | V25: 1 | W25: 4 | X25: =SUM(T25:W25)/16*100 -> 81.25 | Y25: =S25-X25 -> 0 | Z25: =ABS(Y25) -> 0 | AA25: IPE muy similares y ΔIPE pequeño.

Sheet Comparacion_LCT
A1: Caso | B1: Área | C1: Tema | D1: IEE Ref | E1: IEE LCT | F1: Dif IEE | G1: IPE A Ref | H1: IPE A LCT | I1: Dif A | J1: IPE B Ref | K1: IPE B LCT | L1: Dif B | M1: ΔIPE Ref | N1: ΔIPE LCT | O1: Dif Δ | P1: |ΔIPE| Ref | Q1: |ΔIPE| LCT | R1: Observación
A2: PILOT-001 | B2: Redes | C2: Latencia | D2: =Referencia_24!N2 -> 100 | F2: =IF(E2="","",E2-D2) | G2: =Referencia_24!S2 -> 75 | I2: =IF(H2="","",H2-G2) | J2: =Referencia_24!X2 -> 25 | L2: =IF(K2="","",K2-J2) | M2: =Referencia_24!Y2 -> 50 | O2: =IF(N2="","",N2-M2) | P2: =Referencia_24!Z2 -> 50 | Q2: =IF(N2="","",ABS(N2))
A3: PILOT-002 | B3: Bases de datos | C3: Índices | D3: =Referencia_24!N3 -> 100 | F3: =IF(E3="","",E3-D3) | G3: =Referencia_24!S3 -> 81.25 | I3: =IF(H3="","",H3-G3) | J3: =Referencia_24!X3 -> 31.25 | L3: =IF(K3="","",K3-J3) | M3: =Referencia_24!Y3 -> 50 | O3: =IF(N3="","",N3-M3) | P3: =Referencia_24!Z3 -> 50 | Q3: =IF(N3="","",ABS(N3))
A4: PILOT-003 | B4: Redes | C4: TCP | D4: =Referencia_24!N4 -> 100 | F4: =IF(E4="","",E4-D4) | G4: =Referencia_24!S4 -> 62.5 | I4: =IF(H4="","",H4-G4) | J4: =Referencia_24!X4 -> 62.5 | L4: =IF(K4="","",K4-J4) | M4: =Referencia_24!Y4 -> 0 | O4: =IF(N4="","",N4-M4) | P4: =Referencia_24!Z4 -> 0 | Q4: =IF(N4="","",ABS(N4))
A5: PILOT-004 | B5: Sistemas operativos | C5: Memoria virtual | D5: =Referencia_24!N5 -> 100 | F5: =IF(E5="","",E5-D5) | G5: =Referencia_24!S5 -> 81.25 | I5: =IF(H5="","",H5-G5) | J5: =Referencia_24!X5 -> 25 | L5: =IF(K5="","",K5-J5) | M5: =Referencia_24!Y5 -> 56.25 | O5: =IF(N5="","",N5-M5) | P5: =Referencia_24!Z5 -> 56.25 | Q5: =IF(N5="","",ABS(N5))
A6: PILOT-005 | B6: Programación | C6: Recursividad | D6: =Referencia_24!N6 -> 100 | F6: =IF(E6="","",E6-D6) | G6: =Referencia_24!S6 -> 87.5 | I6: =IF(H6="","",H6-G6) | J6: =Referencia_24!X6 -> 62.5 | L6: =IF(K6="","",K6-J6) | M6: =Referencia_24!Y6 -> 25 | O6: =IF(N6="","",N6-M6) | P6: =Referencia_24!Z6 -> 25 | Q6: =IF(N6="","",ABS(N6))
A7: PILOT-006 | B7: Algoritmos | C7: Búsqueda binaria | D7: =Referencia_24!N7 -> 85 | F7: =IF(E7="","",E7-D7) | G7: =Referencia_24!S7 -> 68.75 | I7: =IF(H7="","",H7-G7) | J7: =Referencia_24!X7 -> 56.25 | L7: =IF(K7="","",K7-J7) | M7: =Referencia_24!Y7 -> 12.5 | O7: =IF(N7="","",N7-M7) | P7: =Referencia_24!Z7 -> 12.5 | Q7: =IF(N7="","",ABS(N7))
A8: PILOT-007 | B8: Redes | C8: Modelo OSI | D8: =Referencia_24!N8 -> 20 | F8: =IF(E8="","",E8-D8) | G8: =Referencia_24!S8 -> 75 | I8: =IF(H8="","",H8-G8) | J8: =Referencia_24!X8 -> 12.5 | L8: =IF(K8="","",K8-J8) | M8: =Referencia_24!Y8 -> 62.5 | O8: =IF(N8="","",N8-M8) | P8: =Referencia_24!Z8 -> 62.5 | Q8: =IF(N8="","",ABS(N8))
A9: PILOT-008 | B9: Concurrencia | C9: Condición de carrera | D9: =Referencia_24!N9 -> 65 | F9: =IF(E9="","",E9-D9) | G9: =Referencia_24!S9 -> 87.5 | I9: =IF(H9="","",H9-G9) | J9: =Referencia_24!X9 -> 43.75 | L9: =IF(K9="","",K9-J9) | M9: =Referencia_24!Y9 -> 43.75 | O9: =IF(N9="","",N9-M9) | P9: =Referencia_24!Z9 -> 43.75 | Q9: =IF(N9="","",ABS(N9))
A10: PILOT-009 | B10: Estructuras de datos | C10: Pila y cola | D10: =Referencia_24!N10 -> 35 | F10: =IF(E10="","",E10-D10) | G10: =Referencia_24!S10 -> 87.5 | I10: =IF(H10="","",H10-G10) | J10: =Referencia_24!X10 -> 87.5 | L10: =IF(K10="","",K10-J10) | M10: =Referencia_24!Y10 -> 0 | O10: =IF(N10="","",N10-M10) | P10: =Referencia_24!Z10 -> 0 | Q10: =IF(N10="","",ABS(N10))
A11: PILOT-010 | B11: Bases de datos | C11: Claves | D11: =Referencia_24!N11 -> 45 | F11: =IF(E11="","",E11-D11) | G11: =Referencia_24!S11 -> 81.25 | I11: =IF(H11="","",H11-G11) | J11: =Referencia_24!X11 -> 81.25 | L11: =IF(K11="","",K11-J11) | M11: =Referencia_24!Y11 -> 0 | O11: =IF(N11="","",N11-M11) | P11: =Referencia_24!Z11 -> 0 | Q11: =IF(N11="","",ABS(N11))
A12: PILOT-011 | B12: Seguridad | C12: Hashing | D12: =Referencia_24!N12 -> 100 | F12: =IF(E12="","",E12-D12) | G12: =Referencia_24!S12 -> 93.75 | I12: =IF(H12="","",H12-G12) | J12: =Referencia_24!X12 -> 56.25 | L12: =IF(K12="","",K12-J12) | M12: =Referencia_24!Y12 -> 37.5 | O12: =IF(N12="","",N12-M12) | P12: =Referencia_24!Z12 -> 37.5 | Q12: =IF(N12="","",ABS(N12))
A13: PILOT-012 | B13: Ingeniería de software | C13: Pruebas unitarias | D13: =Referencia_24!N13 -> 100 | F13: =IF(E13="","",E13-D13) | G13: =Referencia_24!S13 -> 81.25 | I13: =IF(H13="","",H13-G13) | J13: =Referencia_24!X13 -> 62.5 | L13: =IF(K13="","",K13-J13) | M13: =Referencia_24!Y13 -> 18.75 | O13: =IF(N13="","",N13-M13) | P13: =Referencia_24!Z13 -> 18.75 | Q13: =IF(N13="","",ABS(N13))
... A25: PILOT-024 | B25: Sistemas distribuidos | C25: Consistencia | D25: =Referencia_24!N25 -> 100 | F25: =IF(E25="","",E25-D25) | G25: =Referencia_24!S25 -> 81.25 | I25: =IF(H25="","",H25-G25) | J25: =Referencia_24!X25 -> 81.25 | L25: =IF(K25="","",K25-J25) | M25: =Referencia_24!Y25 -> 0 | O25: =IF(N25="","",N25-M25) | P25: =Referencia_24!Z25 -> 0 | Q25: =IF(N25="","",ABS(N25))

Sheet Rubrica
A1: NOTA | B1: Las puntuaciones de referencia son una valoración y estrucura de calificación de prueba, no constituyen verdad ni datos oficiales.
A2: IEE | B2: Cada dimensión se puntúa 0-4; IEE = suma/20 × 100.
A3: IEE Semántica | B3: 0 significado distinto; 4 mismo significado conceptual.
A4: IEE Objetivo | B4: 0 tareas diferentes; 4 mismo objetivo.
A5: IEE Cognitivo | B5: 0 nivel cognitivo diferente; 4 equivalente.
A6: IEE Alcance | B6: 0 alcance diferente; 4 mismo alcance.
A7: IEE Neutralidad | B7: 0 reformulación altera la tarea; 4 solo cambia formulación.
A8: IPE | B8: Cada dimensión se puntúa 0-4; IPE = suma/16 × 100.
A9: IPE Definición | B9: 0 ausente; 1 mínima; 2 básica; 3 clara/adecuada; 4 precisa, amplia e integrada.
A10: IPE Causalidad | B10: 0 ausente; 1 superficial; 2 básica; 3 clara/desarrollada; 4 profunda e integrada.
A11: IPE Ejemplificación | B11: 0 ausente; 1 débil; 2 básica; 3 clara/pertinente; 4 altamente pertinente e integrada.
A12: IPE Aplicación | B12: 0 ausente; 1 mínima; 2 básica; 3 clara/contextualizada; 4 desarrollada e integrada.
A13: ΔIPE | B13: IPE A - IPE B. El signo indica dirección; |ΔIPE| expresa magnitud.
